README.rst
setup.py
relay/__init__.py
relay/constants.py
relay/parse.c
relay_framework.egg-info/PKG-INFO
relay_framework.egg-info/SOURCES.txt
relay_framework.egg-info/dependency_links.txt
relay_framework.egg-info/top_level.txt