Metadata-Version: 1.1
Name: relay-framework
Version: 0.1.1
Summary: Relay is an irc micro-framework that smells too much like a web framework
Home-page: https://github.com/ldesgoui/relay
Author: Lucas Desgouilles
Author-email: ldesgoui@gmail.com
License: MIT
Keywords: irc internet relay chat framework
Platform: UNKNOWN
Classifier: Development Status :: 3 - Alpha
Classifier: Topic :: Communications :: Chat :: Internet Relay Chat
Classifier: License :: OSI Approved :: MIT License
Classifier: Programming Language :: Python :: 3.4
